geofacetpy/__init__.py
geofacetpy/geofacetpy.py
geofacetpy-0.1.1.dist-info/LICENSE
geofacetpy-0.1.1.dist-info/METADATA
geofacetpy-0.1.1.dist-info/WHEEL
geofacetpy-0.1.1.dist-info/top_level.txt
geofacetpy-0.1.1.dist-info/RECORD
