Metadata-Version: 2.1
Name: geofacetpy
Version: 0.1.1
Summary: Easily create geofaceted plots in matplotlib
Author-email: Bartłomiej Remlein <bartlomiej@remlein.pl>
License: MIT
Project-URL: Homepage, https://github.com/bartlomiejremlein/geofacetpy
Classifier: Programming Language :: Python :: 3.9
Classifier: Programming Language :: Python :: 3.10
Classifier: Programming Language :: Python :: 3.11
Classifier: License :: OSI Approved :: MIT License
Classifier: Operating System :: OS Independent
Classifier: Topic :: Scientific/Engineering :: Visualization
Requires-Python: >=3.9
License-File: LICENSE
Requires-Dist: matplotlib>=3.5
Requires-Dist: pandas
Provides-Extra: test
Requires-Dist: pytest>=7.0; extra == "test"
Requires-Dist: pytest-cov>=3.0; extra == "test"
Requires-Dist: tox; extra == "test"
Requires-Dist: flake8; extra == "test"
